eero/__init__.py
eero/client.py
eero/eero.py
eero/exception.py
eero/session.py
eero/version.py
eero-0.0.2.dist-info/LICENSE
eero-0.0.2.dist-info/METADATA
eero-0.0.2.dist-info/WHEEL
eero-0.0.2.dist-info/top_level.txt
eero-0.0.2.dist-info/RECORD
