Metadata-Version: 2.1
Name: eero
Version: 0.0.2
Summary: Manage eero network devices
Home-page: https://github.com/343max/eero-client
Author: Max von Webel
Author-email: max@343max.de
License: MIT License
Keywords: eero
Platform: UNKNOWN
Classifier: Development Status :: 4 - Beta
Classifier: Intended Audience :: Developers
Classifier: Natural Language :: English
Classifier: Operating System :: OS Independent
Classifier: Programming Language :: Python
Classifier: Topic :: Software Development :: Libraries :: Python Modules
Classifier: Topic :: Utilities
Classifier: License :: OSI Approved :: MIT License
Requires-Dist: requests
